{"SourceCode": "// SPDX-License-Identifier: MIT\r\npragma solidity ^0.8.0;\r\n\r\ncontract XEDOAIPrivateSale {\r\n    address payable public owner;\r\n    \r\n\r\n   \r\n    mapping(address => uint256) public buyers;\r\n\r\n   \r\n    event Purchase(address indexed buyer, uint256 ethAmount);\r\n\r\n    constructor() {\r\n        owner = payable(msg.sender);\r\n    }\r\n\r\n   \r\n    function buyTokens() public payable {\r\n        \r\n        buyers[msg.sender] += msg.value;\r\n        \r\n        emit Purchase(msg.sender, msg.value);\r\n        \r\n        \r\n    }\r\n\r\n   \r\n    function withdraw() public {\r\n        require(msg.sender == owner, \"You are not the owner.\");\r\n        require(address(this).balance > 0, \"The balance is zero.\");\r\n        \r\n        uint256 balance = address(this).balance;\r\n        owner.transfer(balance);\r\n    }\r\n\r\n   \r\n    function checkContribution(address user) public view returns (uint256) {\r\n        return buyers[user];\r\n    }\r\n}", "ABI": "[{\"inputs\":[],\"stateMutability\":\"nonpayable\",\"type\":\"constructor\"},{\"anonymous\":false,\"inputs\":[{\"indexed\":true,\"internalType\":\"address\",\"name\":\"buyer\",\"type\":\"address\"},{\"indexed\":false,\"internalType\":\"uint256\",\"name\":\"ethAmount\",\"type\":\"uint256\"}],\"name\":\"Purchase\",\"type\":\"event\"},{\"inputs\":[],\"name\":\"buyTokens\",\"outputs\":[],\"stateMutability\":\"payable\",\"type\":\"function\"},{\"inputs\":[{\"internalType\":\"address\",\"name\":\"\",\"type\":\"address\"}],\"name\":\"buyers\",\"outputs\":[{\"internalType\":\"uint256\",\"name\":\"\",\"type\":\"uint256\"}],\"stateMutability\":\"view\",\"type\":\"function\"},{\"inputs\":[{\"internalType\":\"address\",\"name\":\"user\",\"type\":\"address\"}],\"name\":\"checkContribution\",\"outputs\":[{\"internalType\":\"uint256\",\"name\":\"\",\"type\":\"uint256\"}],\"stateMutability\":\"view\",\"type\":\"function\"},{\"inputs\":[],\"name\":\"owner\",\"outputs\":[{\"internalType\":\"address payable\",\"name\":\"\",\"type\":\"address\"}],\"stateMutability\":\"view\",\"type\":\"function\"},{\"inputs\":[],\"name\":\"withdraw\",\"outputs\":[],\"stateMutability\":\"nonpayable\",\"type\":\"function\"}]", "ContractName": "XEDOAIPrivateSale", "CompilerVersion": "v0.8.25+commit.b61c2a91", "OptimizationUsed": "0", "Runs": "200", "ConstructorArguments": "", "EVMVersion": "Default", "Library": "", "LicenseType": "MIT", "Proxy": "0", "Implementation": "", "SwarmSource": "ipfs://af3e87976af4cfa8d80369c5d49b15835f77b21d3f8767738b7937293a947dde"}